ll4mp/__init__.py
ll4mp/courses.py
ll4mp/utils.py
ll4mp_proyect-0.1.0.dist-info/METADATA
ll4mp_proyect-0.1.0.dist-info/WHEEL
ll4mp_proyect-0.1.0.dist-info/top_level.txt
ll4mp_proyect-0.1.0.dist-info/RECORD
