Metadata-Version: 2.4
Name: ll4mp_proyect
Version: 0.1.0
Summary: Un proyecto de ejemplo
Author: Tu Nombre
Author-email: pikp0k4@gmail.com
Dynamic: author
Dynamic: author-email
Dynamic: summary
